aicacia_document_exporter/Document.py
aicacia_document_exporter/DocumentExporter.py
aicacia_document_exporter/PreprocessingModel.py
aicacia_document_exporter/SimpleFileDocumentExporter.py
aicacia_document_exporter/__init__.py
aicacia_document_exporter-0.1.6.dist-info/LICENSE.txt
aicacia_document_exporter-0.1.6.dist-info/METADATA
aicacia_document_exporter-0.1.6.dist-info/WHEEL
aicacia_document_exporter-0.1.6.dist-info/top_level.txt
aicacia_document_exporter-0.1.6.dist-info/RECORD
